CHANGELOG.md
LICENSE
MANIFEST.in
README.md
setup.cfg
setup.py
snakeface/__init__.py
snakeface/argparser.py
snakeface/asgi.py
snakeface/client.py
snakeface/context_processors.py
snakeface/logger.py
snakeface/settings.py
snakeface/settings.yml
snakeface/urls.py
snakeface/version.py
snakeface/wsgi.py
snakeface.egg-info/PKG-INFO
snakeface.egg-info/SOURCES.txt
snakeface.egg-info/dependency_links.txt
snakeface.egg-info/entry_points.txt
snakeface.egg-info/not-zip-safe
snakeface.egg-info/requires.txt
snakeface.egg-info/top_level.txt
snakeface/apps/__init__.py
snakeface/apps/api/__init__.py
snakeface/apps/api/apps.py
snakeface/apps/api/permissions.py
snakeface/apps/api/urls.py
snakeface/apps/api/views.py
snakeface/apps/base/__init__.py
snakeface/apps/base/apps.py
snakeface/apps/base/urls.py
snakeface/apps/base/views.py
snakeface/apps/base/static/favicon.ico
snakeface/apps/base/static/css/bootstrap.min.css
snakeface/apps/base/static/css/custom.css
snakeface/apps/base/static/css/demo.css
snakeface/apps/base/static/css/font-awesome.min.css
snakeface/apps/base/static/css/light-bootstrap-dashboard.css
snakeface/apps/base/static/css/theme-emerald.css
snakeface/apps/base/static/css/themify-icons.css
snakeface/apps/base/static/fonts/FontAwesome.otf
snakeface/apps/base/static/fonts/fontawesome-webfont.eot
snakeface/apps/base/static/fonts/fontawesome-webfont.svg
snakeface/apps/base/static/fonts/fontawesome-webfont.ttf
snakeface/apps/base/static/fonts/fontawesome-webfont.woff
snakeface/apps/base/static/fonts/fontawesome-webfont.woff2
snakeface/apps/base/static/fonts/nucleo-icons.eot
snakeface/apps/base/static/fonts/nucleo-icons.svg
snakeface/apps/base/static/fonts/nucleo-icons.ttf
snakeface/apps/base/static/fonts/nucleo-icons.woff
snakeface/apps/base/static/fonts/nucleo-icons.woff2
snakeface/apps/base/static/fonts/themify.woff
snakeface/apps/base/static/img/clusterb.png
snakeface/apps/base/static/img/compute_server.png
snakeface/apps/base/static/img/favicon.ico
snakeface/apps/base/static/img/grid2.png
snakeface/apps/base/static/img/hero.png
snakeface/apps/base/static/img/logo.png
snakeface/apps/base/static/img/logo_square.png
snakeface/apps/base/static/img/logob.png
